{
 "Rating": "6.7", 
 "Plot": [
  "inspired by charles dickens' \"oliver twist\". a homeless kitten named oliver, roams the streets of new york, where he is taken in by a gang of homeless mutts who survive by stealing from others. during one of these criminal acts, oliver meets a wealthy young girl named jenny foxworth. this meeting will forever change his life.", 
  "a young cat named oliver is left alone in a kitten box, while all the other young cats have new owners. a big dog named dodger shows him how to get food and later oliver lives with him, his owner fagin and fagin's other dogs tito, rita, einstein, and francis. fagin has one problem besides being broke he owes a nasty man named sykes a lot of money. if he can't pay it back he's in big trouble. while oliver runs into a little girl named jenny who becomes his new owner which he is happy with and later sykes sees jenny as the key for him to get his money."
 ], 
 "Writer": [
  "jim cox", 
  "tim disney", 
  "james mangold", 
  "vance gerry", 
  "mike gabriel", 
  "joe ranft", 
  "jim mitchell", 
  "chris bailey", 
  "kirk wise", 
  "david michener", 
  "roger allers", 
  "gary trousdale", 
  "kevin lima", 
  "michael cedeno", 
  "peter young", 
  "leon joosen", 
  "gerrit graham", 
  "sam graham", 
  "chris hubbell", 
  "steve hulett", 
  "danny mann", 
  "charles dickens", 
  "alex mann"
 ], 
 "Synopsis": "", 
 "Cast": [
  "joseph lawrence", 
  "billy joel", 
  "cheech marin", 
  "richard mulligan", 
  "roscoe lee browne", 
  "sheryl lee ralph", 
  "dom deluise", 
  "taurean blacque", 
  "carl weintraub", 
  "robert loggia", 
  "natalie gregory", 
  "william glover", 
  "bette midler", 
  "deborah gates", 
  "charles bartlett", 
  "jonathan brandis", 
  "kal david", 
  "marcia del mar", 
  "victor dimattia", 
  "judi m. durand", 
  "greg finley", 
  "javier grajeda", 
  "robert s. halligan jr.", 
  "j.d. hall", 
  "jo ann harris", 
  "rosanna huffman", 
  "barbara harris", 
  "harvey jason", 
  "karen ichiuji-ramone", 
  "kaleena kiff", 
  "carol king", 
  "mary lee kortes", 
  "rocky krakoff", 
  "david lasley", 
  "christina macgregor", 
  "david mccharen", 
  "john mccurry", 
  "arlin miller", 
  "nancy parent", 
  "whitney rydbeck", 
  "gary schwartz", 
  "vernon scott", 
  "penina segall", 
  "tom snow", 
  "eugene f. van buren", 
  "frank welker", 
  "ruth pointer", 
  "myhanh tran"
 ], 
 "Directors": [
  "george scribner"
 ], 
 "Keywords": [
  "dog", 
  "cat", 
  "new-york", 
  "girl", 
  "terrier", 
  "kidnapping", 
  "no-opening-credits", 
  "loan-shark", 
  "doberman-pinscher", 
  "attempted-murder", 
  "villain", 
  "maturity", 
  "hobo", 
  "thunderstorm", 
  "sex", 
  "2d-animation", 
  "animal-name-in-title", 
  "subway", 
  "afghan-hound", 
  "bulldog", 
  "swimming", 
  "chihuahua", 
  "great-dane", 
  "drowning", 
  "petty-thief", 
  "disney-animated-feature", 
  "new-york-city", 
  "boat", 
  "1980s", 
  "ampersand-in-title", 
  "part-computer-animation", 
  "motorcycle", 
  "birthday", 
  "hit-by-a-train", 
  "poodle", 
  "psychopath", 
  "underwater-scene", 
  "hudson-bay", 
  "wharf", 
  "stealing-food", 
  "smoking", 
  "blockbuster", 
  "based-on-novel", 
  "character-name-in-title"
 ], 
 "Title": "oliver & company"
}