{
 "Rating": "6.4", 
 "Plot": [
  "laurent is the local estate agent, a job that offers easy opportunties for his womanising. his wife beautiful wife loli looks after his home and two children unaware of his many affairs. however, their world is turned upside down by the arrival of marijo, an itinerant lesbian whose minivan breaks down nearby. the neglected loli is drawn to the sensitive marijo and when she learns of laurent's infidelities, invites marijo to move in with them. the arrangement takes an emotional toll on each of them, exacerbated by the arrival of a figure from marijo's past. as they struggle with the situation and each other, all of their lives are changed forever."
 ], 
 "Writer": [
  "patrick aubr\u00e9e", 
  "josiane balasko", 
  "telsche boorman"
 ], 
 "Synopsis": "", 
 "Cast": [
  "victoria abril", 
  "josiane balasko", 
  "alain chabat", 
  "ticky holgado", 
  "catherine hiegel", 
  "catherine samie", 
  "catherine lachens", 
  "katrine boorman", 
  "telsche boorman", 
  "v\u00e9ronique barrault", 
  "sylvie audcoeur", 
  "mich\u00e8le bernier", 
  "maureen diot", 
  "miguel bos\u00e9", 
  "jean-luc violet", 
  "catherine alias", 
  "philippe berry", 
  "paul suissa", 
  "anthony martin", 
  "edmonde franchi", 
  "annick berger", 
  "kostas papadopoulos", 
  "delphine dupont", 
  "henri talau", 
  "arlette lebret", 
  "alexandre grenier", 
  "marie borowski", 
  "blanca li", 
  "h\u00e9l\u00e8ne raimbault", 
  "alice hygoulin", 
  "manuel malou", 
  "javier mart\u00edn cerezo", 
  "vicente almaraz montero", 
  "jean-baptiste marino", 
  "jorge sanchez lopez"
 ], 
 "Directors": [
  "josiane balasko"
 ], 
 "Keywords": [
  "infidelity", 
  "lesbian", 
  "bisexual", 
  "husband-wife-relationship", 
  "nudity", 
  "unfaithfulness", 
  "adultery", 
  "love-triangle", 
  "female-frontal-nudity", 
  "female-nudity", 
  "luberon", 
  "menage-a-trois", 
  "lesbianism", 
  "french", 
  "france", 
  "extramarital-affair", 
  "pregnancy", 
  "bike", 
  "bath", 
  "surprise-ending"
 ], 
 "Title": "gazon maudit"
}