{
 "Rating": "7.4", 
 "Plot": [
  "young parisian mail courier is content with his bohemian lifestyle, his circle of friends and listening to opera, particularly one exceptional american diva who refuses to be recorded. so enamored with her, he makes an illegal tape of her at a concert. but when the tape is confused with one implicating a police chief with the mob, he must use all his ingenuity to survive. particularly notable for its stylish new-wave production values and extended motorcycle chase scene."
 ], 
 "Writer": [
  "daniel odier", 
  "jean-jacques beineix", 
  "jean van hamme", 
  "jean-jacques beineix"
 ], 
 "Synopsis": "", 
 "Cast": [
  "wilhelmenia fernandez", 
  "fr\u00e9d\u00e9ric andr\u00e9i", 
  "richard bohringer", 
  "thuy an luu", 
  "jacques fabbri", 
  "chantal deruaz", 
  "anny romand", 
  "roland bertin", 
  "g\u00e9rard darmon", 
  "dominique pinon", 
  "jean-jacques moreau", 
  "patrick floersheim", 
  "raymond aquilon", 
  "eug\u00e8ne berthier", 
  "g\u00e9rard chaillou", 
  "andr\u00e9e champeaux", 
  "nathalie dalyan", 
  "laurence darpy", 
  "michel debrane", 
  "etienne draber", 
  "laure duthilleul", 
  "nane germon", 
  "gabriel gobin", 
  "jim adhi limas", 
  "louise malapert", 
  "dimo mally", 
  "vaneta mally", 
  "alain marcel", 
  "isabelle mergault", 
  "marthe moudiki-moreau", 
  "jean-luc porraz", 
  "bernard robin", 
  "yann roussel", 
  "brigitte lahaie", 
  "jean-louis vitrac", 
  "tania zabaloieff", 
  "dominique besnehard", 
  "vladimir cosma"
 ], 
 "Directors": [
  "jean-jacques beineix"
 ], 
 "Keywords": [
  "opera", 
  "diva", 
  "new-wave", 
  "chase", 
  "motorcycle", 
  "police", 
  "female-nudity", 
  "legs", 
  "subculture", 
  "girl", 
  "camel-toe", 
  "paris-france", 
  "drugs", 
  "postman", 
  "subway", 
  "policewoman", 
  "topless-female-nudity", 
  "prostitution", 
  "opera-singer", 
  "nudity", 
  "reference-to-beethoven", 
  "corruption", 
  "skirt-flying", 
  "upskirt", 
  "based-on-novel"
 ], 
 "Title": "diva"
}