{
 "Rating": "6.7", 
 "Plot": [
  "steven lidz, unhappy with his home life since his mother got sick, goes and lives with his two crazy uncles. there he changes and gets closer to his uncles, but his parents want him home even though he is finally happy and popular."
 ], 
 "Writer": [
  "franz lidz", 
  "richard lagravenese"
 ], 
 "Synopsis": "", 
 "Cast": [
  "andie macdowell", 
  "john turturro", 
  "michael richards", 
  "maury chaykin", 
  "nathan watt", 
  "anne de salvo", 
  "celia weston", 
  "jack mcgee", 
  "candice azzara", 
  "kendra krull", 
  "giuseppe andrews", 
  "lillian adams", 
  "lou cutell", 
  "sumer stamper", 
  "sean p. donahue", 
  "harold m. schulweis", 
  "zoaunne leroy", 
  "vince melocchi", 
  "charles patrick", 
  "alison chalmers", 
  "chris warfield", 
  "wayne duvall", 
  "andrew craig", 
  "becky ann baker", 
  "mary mercier", 
  "len costanza", 
  "peter kaitlyn", 
  "julie pinson", 
  "zachary bostrom", 
  "thomas brunelle", 
  "joshua boyd", 
  "cody dobson", 
  "colleen ford", 
  "darcy french-myerson", 
  "danielle judovits", 
  "christie mellor", 
  "richard marion", 
  "ruth silveira", 
  "ken tipton"
 ], 
 "Directors": [
  "diane keaton"
 ], 
 "Keywords": [
  "uncle", 
  "ball", 
  "inventor", 
  "1960s", 
  "eccentric", 
  "love", 
  "terminal-illness", 
  "paranoia", 
  "cancer", 
  "jewish-culture", 
  "dysfunctional-family", 
  "cemetery", 
  "mother-son-relationship", 
  "title-directed-by-female", 
  "death-in-family", 
  "childhood-memory", 
  "affection", 
  "individuality", 
  "teen-angst", 
  "hoarding", 
  "based-on-book"
 ], 
 "Title": "unstrung heroes"
}